scim_client/__init__.py
scim_client/_version.py
scim_client/defaults.py
scim_client/resources.py
scim_client/response.py
scim_client/scim_client.py
scim_client/utils.py
scim_client-0.2.3.dist-info/licenses/AUTHORS.rst
scim_client-0.2.3.dist-info/licenses/LICENSE
scim_client-0.2.3.dist-info/METADATA
scim_client-0.2.3.dist-info/WHEEL
scim_client-0.2.3.dist-info/top_level.txt
scim_client-0.2.3.dist-info/RECORD
