Metadata-Version: 2.4
Name: scim_client
Version: 0.2.3
Summary: SCIM v2 API client
Home-page: https://github.com/Aplopio/python-scim-client
Author: Mitratech Development Team
Author-email: devs@mitratech.com
License: MIT license
Keywords: scim_client
Classifier: Development Status :: 4 - Beta
Classifier: Intended Audience :: Developers
Classifier: License :: OSI Approved :: MIT License
Classifier: Natural Language :: English
Classifier: Programming Language :: Python :: 3.8
Classifier: Programming Language :: Python :: 3.9
Classifier: Programming Language :: Python :: 3.10
Classifier: Programming Language :: Python :: 3.11
Classifier: Programming Language :: Python :: 3.12
Requires-Python: >=3.8
License-File: LICENSE
License-File: AUTHORS.rst
Dynamic: author
Dynamic: author-email
Dynamic: classifier
Dynamic: description
Dynamic: home-page
Dynamic: keywords
Dynamic: license
Dynamic: license-file
Dynamic: requires-python
Dynamic: summary
